file_scan_dd/__init__.py
file_scan_dd/file_scan_dd.py
file_scan_dd-1.2.dist-info/METADATA
file_scan_dd-1.2.dist-info/WHEEL
file_scan_dd-1.2.dist-info/top_level.txt
file_scan_dd-1.2.dist-info/RECORD
